koala_formatter/__init__.py
koala_formatter/exceptions/__init__.py
koala_formatter/exceptions/exceptions.py
koala_formatter/formatters/__init__.py
koala_formatter/formatters/formatter_base.py
koala_formatter/formatters/utils.py
koala_formatter/formatters/db/__init__.py
koala_formatter/formatters/db/oracle_formatter.py
koala_formatter/formatters/db/postgres_formatter.py
koala_formatter/formatters/db/tableau_formatter.py
koala_formatter/formatters/graph_objects/__init__.py
koala_formatter/formatters/graph_objects/graph_edge.py
koala_formatter/formatters/graph_objects/graph_node.py
koala_formatter/formatters/graph_objects/graph_object_base.py
koala_formatter/formatters/kafka/__init__.py
koala_formatter/formatters/kafka/kafka_formatter.py
tests/__init__.py
tests/koala_formatter/__init__.py
tests/koala_formatter/formatters/__init__.py
tests/koala_formatter/formatters/db/__init__.py
tests/koala_formatter/formatters/db/test_oracle_formatter.py
tests/koala_formatter/formatters/db/test_postgres_formatter.py
tests/koala_formatter/formatters/db/test_tableau_formatter.py
tests/koala_formatter/formatters/db/test_utils/__init__.py
tests/koala_formatter/formatters/db/test_utils/expected_edges.py
tests/koala_formatter/formatters/db/test_utils/expected_nodes.py
tests/koala_formatter/formatters/db/test_utils/nodes.py
tests/koala_formatter/formatters/db/test_utils/properties.py
tests/koala_formatter/formatters/kafka/__init__.py
tests/koala_formatter/formatters/kafka/test_kafka_formatter.py
tests/koala_formatter/formatters/kafka/test_utils/__init__.py
tests/koala_formatter/formatters/kafka/test_utils/nodes.py
tests/koala_formatter/formatters/kafka/test_utils/properties.py
tests/koala_formatter/graph_objects/__init__.py
tests/koala_formatter/graph_objects/test_graph_edge.py
tests/koala_formatter/graph_objects/test_graph_node.py
tests/koala_formatter/graph_objects/test_graph_object_base.py
tests/koala_formatter/graph_objects/test_utils.py
koala_formatter-0.1.3.dist-info/METADATA
koala_formatter-0.1.3.dist-info/WHEEL
koala_formatter-0.1.3.dist-info/top_level.txt
koala_formatter-0.1.3.dist-info/RECORD
